setup.py
mmxtest/mmxtest.py
mmxtest.egg-info/PKG-INFO
mmxtest.egg-info/SOURCES.txt
mmxtest.egg-info/dependency_links.txt
mmxtest.egg-info/top_level.txt