Metadata-Version: 1.0
Name: mmxtest
Version: 1.0.6
Summary: A print test for PyPI
Home-page: https://www.python.org/
Author: mmx
Author-email: mingxing157157@163.com
License: UNKNOWN
Platform: UNKNOWN
